quizie/__init__.py
quizie/quiz.py
quizie-0.1.8.dist-info/licenses/LICENSE
quizie-0.1.8.dist-info/METADATA
quizie-0.1.8.dist-info/WHEEL
quizie-0.1.8.dist-info/top_level.txt
quizie-0.1.8.dist-info/RECORD
